setup.py
src/orionclient.py
src/orionclient.egg-info/PKG-INFO
src/orionclient.egg-info/SOURCES.txt
src/orionclient.egg-info/dependency_links.txt
src/orionclient.egg-info/requires.txt
src/orionclient.egg-info/top_level.txt
test/test.py
test/test_settings.py