Metadata-Version: 1.1
Name: orionclient
Version: 0.0.1
Summary: pure python fiware orion client
Home-page: https://github.com/openath/orion-python-client
Author: Andy Robinson
Author-email: andy@reportlab.com
License: BSD
Keywords: orion client
Platform: UNKNOWN
Classifier: Development Status :: 3 - Alpha
Classifier: Intended Audience :: Developers
Classifier: Topic :: Software Development :: Libraries :: Python Modules
Classifier: Programming Language :: Python :: 2
Classifier: Programming Language :: Python :: 2.7
Classifier: Programming Language :: Python :: 3
Classifier: Programming Language :: Python :: 3.3
Classifier: Programming Language :: Python :: 3.4
Classifier: Programming Language :: Python :: 3.5
